neuromeka/__init__.py
neuromeka/ecat.py
neuromeka/eye.py
neuromeka/indy.py
neuromeka/indy_client3.py
neuromeka/moby.py
neuromeka/motor.py
neuromeka/indy_dcp/__init__.py
neuromeka/indy_dcp/indy_program_maker.py
neuromeka/indy_dcp/indydcp_client.py
neuromeka/proto/EtherCATCommgRPCServer_pb2.py
neuromeka/proto/EtherCATCommgRPCServer_pb2_grpc.py
neuromeka/proto/EyeTask_pb2.py
neuromeka/proto/EyeTask_pb2_grpc.py
neuromeka/proto/IndygRPCTask_pb2.py
neuromeka/proto/IndygRPCTask_pb2_grpc.py
neuromeka/proto/MobygRPCServer_pb2.py
neuromeka/proto/MobygRPCServer_pb2_grpc.py
neuromeka/proto/MotorControlgRPCServer_pb2.py
neuromeka/proto/MotorControlgRPCServer_pb2_grpc.py
neuromeka/proto/__init__.py
neuromeka/proto/control_msgs_pb2.py
neuromeka/proto/control_msgs_pb2_grpc.py
neuromeka/proto/control_pb2.py
neuromeka/proto/control_pb2_grpc.py
neuromeka/proto/grpc_wrapper.py
neuromeka/proto/shared_msgs_pb2.py
neuromeka/proto/shared_msgs_pb2_grpc.py
neuromeka_clients-0.1.12.dist-info/LICENSE
neuromeka_clients-0.1.12.dist-info/METADATA
neuromeka_clients-0.1.12.dist-info/WHEEL
neuromeka_clients-0.1.12.dist-info/top_level.txt
neuromeka_clients-0.1.12.dist-info/RECORD
